satellome/__init__.py
satellome/__main__.py
satellome/constants.py
satellome/install_command.py
satellome/main.py
satellome/redraw.py
satellome/settings.yaml
satellome/trc_set_tr_names_color.py
satellome/core_functions/__init__.py
satellome/core_functions/classification_micro.py
satellome/core_functions/exceptions.py
satellome/core_functions/settings.py
satellome/core_functions/trf_clusters.py
satellome/core_functions/trf_drawing.py
satellome/core_functions/trf_embedings.py
satellome/core_functions/io/__init__.py
satellome/core_functions/io/abstract_reader.py
satellome/core_functions/io/block_file.py
satellome/core_functions/io/fasta_file.py
satellome/core_functions/io/file_system.py
satellome/core_functions/io/gff_file.py
satellome/core_functions/io/tab_file.py
satellome/core_functions/io/tr_file.py
satellome/core_functions/io/trf_file.py
satellome/core_functions/models/__init__.py
satellome/core_functions/models/abstract_model.py
satellome/core_functions/models/gff3_model.py
satellome/core_functions/models/trf_model.py
satellome/core_functions/tools/__init__.py
satellome/core_functions/tools/bed_tools.py
satellome/core_functions/tools/clusterization.py
satellome/core_functions/tools/distances.py
satellome/core_functions/tools/gene_intersect.py
satellome/core_functions/tools/gene_intersect_streaming.py
satellome/core_functions/tools/kmer_splitting.py
satellome/core_functions/tools/ncbi.py
satellome/core_functions/tools/parsers.py
satellome/core_functions/tools/processing.py
satellome/core_functions/tools/reports.py
satellome/core_functions/tools/statistics.py
satellome/core_functions/tools/trf_tools.py
satellome/core_functions/tools/validation.py
satellome/installers/__init__.py
satellome/installers/base.py
satellome/installers/fastan.py
satellome/installers/tanbed.py
satellome/installers/trf_large.py
satellome/installers/trf_standard.py
satellome/steps/__init__.py
satellome/steps/trf_classify.py
satellome/steps/trf_draw.py
satellome/steps/trf_parse_raw.py
satellome-1.6.1.dist-info/licenses/LICENSE
satellome-1.6.1.dist-info/METADATA
satellome-1.6.1.dist-info/WHEEL
satellome-1.6.1.dist-info/entry_points.txt
satellome-1.6.1.dist-info/top_level.txt
satellome-1.6.1.dist-info/RECORD
