Metadata-Version: 2.4
Name: satellome
Version: 1.6.1
Summary: A comprehensive tool for satellite DNA analysis in T2T genome assemblies
Home-page: https://github.com/aglabx/Satellome
Author: Aleksey Komissarov
Author-email: Aleksey Komissarov <ad3002@gmail.com>
License: MIT
Project-URL: Homepage, https://github.com/aglabx/satellome
Project-URL: Documentation, https://github.com/aglabx/satellome/wiki
Project-URL: Repository, https://github.com/aglabx/satellome
Project-URL: Issues, https://github.com/aglabx/satellome/issues
Classifier: Development Status :: 4 - Beta
Classifier: Environment :: Console
Classifier: Intended Audience :: Science/Research
Classifier: Operating System :: OS Independent
Classifier: Programming Language :: Python :: 3
Classifier: Programming Language :: Python :: 3.6
Classifier: Programming Language :: Python :: 3.7
Classifier: Programming Language :: Python :: 3.8
Classifier: Programming Language :: Python :: 3.9
Classifier: Programming Language :: Python :: 3.10
Classifier: Programming Language :: Python :: 3.11
Classifier: Topic :: Scientific/Engineering :: Bio-Informatics
Requires-Python: >=3.6
License-File: LICENSE
Requires-Dist: PyExp
Requires-Dist: numpy
Requires-Dist: pyyaml
Requires-Dist: simplejson
Requires-Dist: intervaltree
Requires-Dist: tqdm
Requires-Dist: plotly
Requires-Dist: editdistance
Requires-Dist: networkx
Requires-Dist: matplotlib
Dynamic: author
Dynamic: home-page
Dynamic: license-file
Dynamic: requires-python
